[
    {
        "surname": "Khan",
        "awards": 10,
        "education": "University of Malaya, COMSATS University, Technische Universität Ilmenau"
    },
    {
        "surname": "Aalst",
        "awards": 0,
        "education": "Technische Universiteit Eindhoven"
    },
    {
        "surname": "Aaronson",
        "awards": 7,
        "education": "Cornell University, University of California"
    },
    {
        "surname": "Abebe",
        "awards": 9,
        "education": "Nazareth School, International Community School of Addis Ababa"
    },
    {
        "surname": "Abelson",
        "awards": 5,
        "education": "Princeton University"
    },
    {
        "surname": "Abiteboul",
        "awards": 4,
        "education": "Télécom Paris"
    },
    {
        "surname": "Abramsky",
        "awards": 6,
        "education": "King's College, University of London"
    },
    {
        "surname": "Adleman",
        "awards": 1,
        "education": "University of California"
    },
    {
        "surname": "Agrawal",
        "awards": 10,
        "education": "Indian Institute of Technology Kanpur"
    },
    {
        "surname": "Ahn",
        "awards": 3,
        "education": "American School of Guatemala"
    },
    {
        "surname": "Aho",
        "awards": 7,
        "education": "University of Toronto, Princeton University"
    },
    {
        "surname": "Allen",
        "awards": 6,
        "education": "Wesleyan University, University of Wisconsin–Madison"
    },
    {
        "surname": "Amdahl",
        "awards": 2,
        "education": "South Dakota State University"
    },
    {
        "surname": "Anderson",
        "awards": 2,
        "education": "Wesleyan University, University of Wisconsin–Madison"
    },
    {
        "surname": "Anthony",
        "awards": 6,
        "education": "Drexel University"
    },
    {
        "surname": "Appel",
        "awards": 0,
        "education": "Princeton University, Carnegie Mellon University"
    },
    {
        "surname": "Aragon",
        "awards": 1,
        "education": "California Institute of Technology, University of California"
    },
    {
        "surname": "Arden",
        "awards": 0,
        "education": "Purdue University"
    },
    {
        "surname": "Jones",
        "awards": 0,
        "education": "Tennessee State University, North Carolina State University"
},   
{
      "surname": "Arora",
      "awards": 0,
      "education": "Massachusetts Institute of Technology"
   },
   {
      "surname": "Asprey",
      "awards": 0,
      "education": "Vassar College, University of Iowa"
   },
   {
      "surname": "Atanasoff",
      "awards": 1,
      "education": "University of Florida"
   },
   {
      "surname": "Atre",
      "awards": 0,
      "education": "University of Poona, University of Heidelberg"
   },
   {
      "surname": "Augustsson",
      "awards": 0,
      "education": "Chalmers University of Technology"
   },
   {
      "surname": "Babbage",
      "awards": 1,
      "education": "Peterhouse, Cambridge"
   },
   {
      "surname": "Bachman",
      "awards": 5,
      "education": "University of Pennsylvania, Michigan State University"
   },
   {
      "surname": "Backhouse",
      "awards": 0,
      "education": "Churchill College, Imperial College"
   },
   {
      "surname": "Backus",
      "awards": 9,
      "education": "University of Virginia, University of Pittsburgh, Haverford College, Columbia University"
   },
   {
      "surname": "Bacon",
      "awards": 1,
      "education": "University of California"
   },
   {
      "surname": "Bader",
      "awards": 1,
      "education": "Liberty High School"
   },
   {
      "surname": "Bahl",
      "awards": 17,
      "education": "University of Massachusetts, University at Buffalo"
   },
   {
      "surname": "Barr",
      "awards": 0,
      "education": "University of Massachusetts"
   },
   {
      "surname": "Bartik",
      "awards": 4,
      "education": "University of California"
   },
   {
      "surname": "Barto",
      "awards": 1,
      "education": "University of Michigan"
   },
   {
      "surname": "Bauer",
      "awards": 14,
      "education": "Ludwig Maximilians Universität"
   },
   {
      "surname": "Bayer",
      "awards": 2,
      "education": "University of Illinois"
   },
   {
      "surname": "Bell",
      "awards": 8,
      "education": "Massachusetts Institute of Technology"
   },
   {
      "surname": "Bellovin",
      "awards": 0,
      "education": "Columbia University"
   },
   {
      "surname": "Berdichevsky",
      "awards": 0,
      "education": "St. Petersburg State Polytechnic University"
   },
   {
      "surname": "Berners-Lee",
      "awards": 9,
      "education": "The Queen's College"
   },
   {
      "surname": "Bernstein",
      "awards": 0,
      "education": "University of California, New York University"
   },
   {
      "surname": "Bernus",
      "awards": 0,
      "education": "Budapest Technical University, University of Queensland"
   },
   {
      "surname": "Bezos",
      "awards": 0,
      "education": "Princeton University"
   },
   {
      "surname": "Bhushan",
      "awards": 0,
      "education": "Indian Institute of Technology, Massachusetts Institute of Technology"
   },
   {
      "surname": "Bjørner",
      "awards": 3,
      "education": "Technical University of Denmark"
   },
   {
      "surname": "Blaauw",
      "awards": 0,
      "education": "Delft University of Technology, Harvard University"
   },
   {
      "surname": "Black",
      "awards": 1,
      "education": "University of London"
   },
   {
      "surname": "Blei",
      "awards": 2,
      "education": "Brown University, University of California"
   },
   {
      "surname": "Blum",
      "awards": 0,
      "education": "Brooklyn College"
   },
   {
      "surname": "Blum",
      "awards": 3,
      "education": "Carnegie Institute of Technology, Simmons College"
   },
   {
      "surname": "Blum",
      "awards": 4,
      "education": "Massachusetts Institute of Technology"
   },
   {
      "surname": "Boehm",
      "awards": 12,
      "education": "Harvard University"
   },
   {
      "surname": "Böhm",
      "awards": 0,
      "education": "ETH Zürich"
   },
   {
      "surname": "Bollacker",
      "awards": 0,
      "education": "University of California"
   },
   {
      "surname": "Bonwick",
      "awards": 0,
      "education": "Massachusetts Institute of Technology"
   },
   {
      "surname": "Booch",
      "awards": 2,
      "education": "United States Air Force Academy, University of California"
   },
   {
      "surname": "Boole",
      "awards": 0,
      "education": "Bainbridge's Commercial Academy"
   },
   {
      "surname": "Booth",
      "awards": 0,
      "education": "Jesus College"
   },
   {
      "surname": "Booth",
      "awards": 0,
      "education": "University of London"
   },
   {
      "surname": "Borg",
      "awards": 8,
      "education": "New York University"
   },
   {
      "surname": "Bos",
      "awards": 0,
      "education": "University of Groningen"
   },
   {
      "surname": "Botvinnik",
      "awards": 0,
      "education": "New York University"
   },
   {
      "surname": "Bowen",
      "awards": 1,
      "education": "Oxford University"
   },
   {
      "surname": "Bourne",
      "awards": 3,
      "education": "King's College, Trinity College, Cambridge"
   },
   {
      "surname": "Bouwman",
      "awards": 0,
      "education": "University of Amsterdam"
   },
   {
      "surname": "Boyer",
      "awards": 0,
      "education": "Oxford University"
   },
   {
      "surname": "Brandenburg",
      "awards": 1,
      "education": "University of Erlangen-Nuremberg"
   },
   {
      "surname": "Brassard",
      "awards": 3,
      "education": "Cornell University"
   },
   {
      "surname": "Breed",
      "awards": 1,
      "education": "Stanford University"
   },
   {
      "surname": "Bresenham",
      "awards": 0,
      "education": "Winthrop University"
   },
   {
      "surname": "Brin",
      "awards": 6,
      "education": "Moscow State University"
   },
   {
      "surname": "Brown",
      "awards": 0,
      "education": "University of Pennsylvania"
   },
   {
      "surname": "Brinch Hansen",
      "awards": 1,
      "education": "Technical University of Denmark"
   },
   {
      "surname": "Brinkkemper",
      "awards": 0,
      "education": "University of Amsterdam, Radboud University"
   },
   {
      "surname": "Brooks",
      "awards": 25,
      "education": "Duke University, Harvard University"
   },
   {
      "surname": "Brooks",
      "awards": 1,
      "education": "Stanford University, Flinders University"
   },
   {
      "surname": "Burnett",
      "awards": 0,
      "education": "Miami University"
   },
   {
      "surname": "Butler",
      "awards": 0,
      "education": "Trinity College, Wolfson College"
   },
   {
      "surname": "Caballero Gil",
      "awards": 3,
      "education": "University of La Laguna"
   },
   {
      "surname": "Camp",
      "awards": 2,
      "education": "The College of William and Mary, Michigan State University, Kalamazoo College"
   },
   {
      "surname": "Campbell-Kelly",
      "awards": 0,
      "education": "Sunderland Polytechnic"
   },
   {
      "surname": "Candlin",
      "awards": 0,
      "education": "University of Cambridge"
   },
   {
      "surname": "Canion",
      "awards": 0,
      "education": "University of Houston"
   },
   {
      "surname": "Cantrill",
      "awards": 0,
      "education": "Brown University"
   },
   {
      "surname": "Cardelli",
      "awards": 3,
      "education": "University of Pisa, University of Edinburgh"
   },
   {
      "surname": "Carmack",
      "awards": 0,
      "education": "Brown University"
   },
   {
      "surname": "Caspersen",
      "awards": 8,
      "education": "Aarhus University"
   },
   {
      "surname": "Catmull",
      "awards": 4,
      "education": "University of Utah"
   },
   {
      "surname": "Cerf",
      "awards": 38,
      "education": "Stanford University, University of California"
   },
   {
      "surname": "Chaitin",
      "awards": 0,
      "education": "Brown University"
   },
   {
      "surname": "Cailliau",
      "awards": 13,
      "education": "Ghent University, University of Michigan"
   },
   {
      "surname": "Chaochen",
      "awards": 1,
      "education": "Peking University, Chinese Academy of Sciences"
   },
   {
      "surname": "Chen",
      "awards": 7,
      "education": "National Taiwan University, Harvard University"
   },
   {
      "surname": "Chiariglione",
      "awards": 7,
      "education": "Polytechnic University of Turin, University of Tokyo"
   },
   {
      "surname": "Chou",
      "awards": 0,
      "education": "Stanford University"
   },
   {
      "surname": "Church",
      "awards": 0,
      "education": "Princeton University"
   },
   {
      "surname": "Ciaramella",
      "awards": 0,
      "education": "La Sapienza University"
   },
   {
      "surname": "Clarke",
      "awards": 1,
      "education": "Cornell University"
   },
   {
      "surname": "Cocke",
      "awards": 6,
      "education": "Duke University"
   },
   {
      "surname": "Codd",
      "awards": 1,
      "education": "Exeter College, University of Michigan"
   },
   {
      "surname": "Cohen",
      "awards": 0,
      "education": "State University of Minas Geraes"
   },
   {
      "surname": "Coldwater",
      "awards": 0,
      "education": "Brown University"
   },
   {
      "surname": "Colton",
      "awards": 0,
      "education": "University of Durham, University of Liverpool"
   },
   {
      "surname": "Colmerauer",
      "awards": 0,
      "education": "Grenoble Institute of Technology"
   },
   {
      "surname": "Comer",
      "awards": 8,
      "education": "Houghton College, Pennsylvania State University"
   },
   {
      "surname": "Compton",
      "awards": 0,
      "education": "University of new South Wales"
   },
   {
      "surname": "Conway",
      "awards": 2,
      "education": "University of Wisconsin"
   },
   {
      "surname": "Cormack",
      "awards": 0,
      "education": "University of Waterloo"
   },
   {
      "surname": "Cook",
      "awards": 8,
      "education": "Harvard University, University of Michigan"
   },
   {
      "surname": "Cooley",
      "awards": 0,
      "education": "Manhattan College, Columbia University"
   },
   {
      "surname": "Cooper",
      "awards": 0,
      "education": "University of California"
   },
   {
      "surname": "Corbató",
      "awards": 2,
      "education": "California Institute of Technology, Massachusetts Institute of Technology"
   },
   {
      "surname": "Cosper",
      "awards": 0,
      "education": "Brown University"
   },
   {
      "surname": "Cousot",
      "awards": 8,
      "education": "Université Joseph Fourier Grenoble"
   },
   {
      "surname": "Cox",
      "awards": 4,
      "education": "University College London, Oxford University"
   },
   {
      "surname": "Coyle",
      "awards": 0,
      "education": "Ulster University"
   },
   {
      "surname": "Cray",
      "awards": 0,
      "education": "University of Minnesota"
   },
   {
      "surname": "Cristianini",
      "awards": 1,
      "education": "University of Trieste, University of London, University of Bristol"
   },
   {
      "surname": "Crowcroft",
      "awards": 3,
      "education": "University of Cambridge"
   },
   {
      "surname": "Croft",
      "awards": 0,
      "education": "Monash University, University of Cambridge"
   },
   {
      "surname": "Culler",
      "awards": 5,
      "education": "University of California"
   },
   {
      "surname": "Curry",
      "awards": 0,
      "education": "Harvard University, University of Göttingen"
   },
   {
      "surname": "Dadda",
      "awards": 0,
      "education": "Politecnico di Milano"
   },
   {
      "surname": "Dahl",
      "awards": 2,
      "education": "University of Oslo"
   },
   {
      "surname": "Dahl",
      "awards": 0,
      "education": "UC San Diego, University of Rochester"
   },
   {
      "surname": "Dam",
      "awards": 0,
      "education": "Brown University"
   },
   {
      "surname": "Das",
      "awards": 0,
      "education": "Georgia Tech, Indian Institute of Science, Jadavpur University"
   },
   {
      "surname": "Daswani",
      "awards": 0,
      "education": "Stanford University, Columbia University"
   },
   {
      "surname": "Date",
      "awards": 0,
      "education": "University of Cambridge"
   },
   {
      "surname": "Davis",
      "awards": 0,
      "education": "Arizona State University"
   },
   {
      "surname": "Dean",
      "awards": 6,
      "education": "University of Minnesota"
   },
   {
      "surname": "Demaine",
      "awards": 3,
      "education": "Brown University"
   },
   {
      "surname": "DeMarco",
      "awards": 1,
      "education": "Cornell University, University of Paris"
   },
   {
      "surname": "DeMillo",
      "awards": 0,
      "education": "University of St. Thomas, Georgia Tech"
   },
   {
      "surname": "Denning",
      "awards": 9,
      "education": "University of Michigan, Purdue University"
   },
   {
      "surname": "Denning",
      "awards": 2,
      "education": "Cornell University"
   },
   {
      "surname": "Dertouzos",
      "awards": 0,
      "education": "University of Athens, Massachusetts Institute of Technology"
   },
   {
      "surname": "Dewdney",
      "awards": 0,
      "education": "Cornell University"
   },
   {
      "surname": "Dewar",
      "awards": 0,
      "education": "University of Chicago"
   },
   {
      "surname": "Dham",
      "awards": 0,
      "education": "Delhi College of Engineering, Delhi Technological University, Delhi University, University of Cincinnati"
   },
   {
      "surname": "Dietz",
      "awards": 0,
      "education": "Eindhoven University of Technology"
   },
   {
      "surname": "Diffie",
      "awards": 4,
      "education": "City College of New York"
   },
   {
      "surname": "Dijkstra",
      "awards": 10,
      "education": "Leiden University, University of Amsterdam"
   },
   {
      "surname": "Dillon",
      "awards": 0,
      "education": "University of California"
   },
   {
      "surname": "Dix",
      "awards": 0,
      "education": "Cornell University"
   },
   {
      "surname": "Dongarra",
      "awards": 5,
      "education": "Chicago State University, University of New Mexico"
   },
   {
      "surname": "Dorigo",
      "awards": 0,
      "education": "Cornell University"
   },
   {
      "surname": "Dourish",
      "awards": 5,
      "education": "Cornell University"
   },
   {
      "surname": "Draper",
      "awards": 6,
      "education": "University of Missouri, Stanford University"
   },
   {
      "surname": "Dumais",
      "awards": 1,
      "education": "Indiana University, Bates College"
   },
   {
      "surname": "Dunkels",
      "awards": 0,
      "education": "Swedish Institute of Computer Science"
   },
   {
      "surname": "Dunn",
      "awards": 11,
      "education": "Cornell University"
   },
   {
      "surname": "Dustdar",
      "awards": 0,
      "education": "TU Wien"
   },
   {
      "surname": "Eades",
      "awards": 0,
      "education": "Cornell University"
   },
   {
      "surname": "Easley",
      "awards": 0,
      "education": "Indiana University"
   },
   {
      "surname": "Ebbinkhuijsen",
      "awards": 0,
      "education": "University of Amsterdam"
   },
   {
      "surname": "Eckert",
      "awards": 4,
      "education": "University of Pennsylvania"
   },
   {
      "surname": "Edelman",
      "awards": 5,
      "education": "Yale University, Massachusetts Institute of Technology"
   },
   {
      "surname": "Eich",
      "awards": 0,
      "education": "University of Illinois, Santa Clara University"
   },
   {
      "surname": "Emeagwali",
      "awards": 0,
      "education": "University of London, Oregon State University, University of Maryland"
   },
   {
      "surname": "Emerson",
      "awards": 2,
      "education": "University of Texas, Harvard University"
   },
   {
      "surname": "Engelbart",
      "awards": 7,
      "education": "Yale University"
   },
   {
      "surname": "Engelhardt",
      "awards": 1,
      "education": "Stanford University, University of California"
   },
   {
      "surname": "Eppstein",
      "awards": 0,
      "education": "Stanford University, Columbia University"
   },
   {
      "surname": "Yershov",
      "awards": 0,
      "education": "Moscow State University"
   },
   {
      "surname": "Estridge",
      "awards": 0,
      "education": "University of Florida"
   },
   {
      "surname": "Etzioni",
      "awards": 6,
      "education": "Harvard University, Carnegie Mellon University"
   },
   {
      "surname": "Evans",
      "awards": 0,
      "education": "University College London, University of Reading"
   },
   {
      "surname": "Evans",
      "awards": 1,
      "education": "University of Utah"
   },
   {
      "surname": "Even",
      "awards": 0,
      "education": "Harvard University"
   },
   {
      "surname": "Fahlman",
      "awards": 1,
      "education": "Massachusetts Institute of Technology"
   },
   {
      "surname": "Feigenbaum",
      "awards": 4,
      "education": "Yale University"
   },
   {
      "surname": "Felten",
      "awards": 2,
      "education": "California Institute of Technology, University of Washington"
   },
   {
      "surname": "Finin",
      "awards": 1,
      "education": "Massachusetts Institute of Technology"
},   
{
      "surname": "Finkel",
      "awards": 0,
      "education": "University of Chicago, Stanford University"
   },
   {
      "surname": "Firesmith",
      "awards": 0,
      "education": "Arizona State University"
   },
   {
      "surname": "Flake",
      "awards": 0,
      "education": "Massachusetts Institute of Technology"
   },
   {
      "surname": "Flowers",
      "awards": 0,
      "education": "University of London"
   },
   {
      "surname": "Floyd",
      "awards": 2,
      "education": "University of Chicago"
   },
   {
      "surname": "Floyd",
      "awards": 2,
      "education": "University of California"
   },
   {
      "surname": "Fogel",
      "awards": 0,
      "education": "New York University, Rutgers University, University of California"
   },
   {
      "surname": "Foley",
      "awards": 1,
      "education": "Lehigh University, University of Michigan"
   },
   {
      "surname": "Forbus",
      "awards": 0,
      "education": "Massachusetts Institute of Technology"
   },
   {
      "surname": "Ford",
      "awards": 0,
      "education": "Massachusetts Institute of Technology"
   },
   {
      "surname": "Fortnow",
      "awards": 4,
      "education": "Cornell University, Massachusetts Institute of Technology"
   },
   {
      "surname": "Fayed",
      "awards": 0,
      "education": "Menoufia University, King Saud University"
   },
   {
      "surname": "Fowler",
      "awards": 0,
      "education": "University College London"
   },
   {
      "surname": "France",
      "awards": 1,
      "education": "University of the West Indies, Massey University"
   },
   {
      "surname": "Franke",
      "awards": 9,
      "education": "Cornell University"
   },
   {
      "surname": "Fredkin",
      "awards": 1,
      "education": "Cornell University"
   },
   {
      "surname": "Freund",
      "awards": 1,
      "education": "The Hebrew University of Jerusalem, University of California"
   },
   {
      "surname": "Friedman",
      "awards": 0,
      "education": "University of Houston"
   },
   {
      "surname": "Fischer",
      "awards": 8,
      "education": "University of British Columbia, Cambridge University"
   },
   {
      "surname": "Fu",
      "awards": 9,
      "education": "Nanjing University of Aeronautics and Astronautics"
   },
   {
      "surname": "Fu",
      "awards": 6,
      "education": "Northeastern University, Universität Göttingen"
   },
   {
      "surname": "Fukushima",
      "awards": 1,
      "education": "Kyoto University, Osaka University"
   },
   {
      "surname": "Fulkerson",
      "awards": 1,
      "education": "Southern Illinois University"
   },
   {
      "surname": "Gabriel",
      "awards": 2,
      "education": "Northeastern University, Massachusetts Institute of Technology, University of Illinois, Stanford University"
   },
   {
      "surname": "Galil",
      "awards": 3,
      "education": "Tel Aviv University, Cornell University"
   },
   {
      "surname": "Galler",
      "awards": 0,
      "education": "University of Chicago"
   },
   {
      "surname": "García-Molina",
      "awards": 1,
      "education": "Monterrey Institute of Technology, Stanford University"
   },
   {
      "surname": "Garey",
      "awards": 0,
      "education": "University of Wisconsin–Madison"
   },
   {
      "surname": "Garis",
      "awards": 0,
      "education": "Cornell University"
   },
   {
      "surname": "Gates",
      "awards": 4,
      "education": "Cornell University"
   },
   {
      "surname": "Gelernter",
      "awards": 1,
      "education": "State University of New York"
   },
   {
      "surname": "Gelobter",
      "awards": 0,
      "education": "Brown University"
   },
   {
      "surname": "Geschke",
      "awards": 3,
      "education": "Cornell University"
   },
   {
      "surname": "Ghahramani",
      "awards": 1,
      "education": "University of Pennsylvania, Massachusetts Institute of Technology"
   },
   {
      "surname": "Ghemawat",
      "awards": 1,
      "education": "Cornell University, Massachusetts Institute of Technology"
   },
   {
      "surname": "Gibbons",
      "awards": 0,
      "education": "University of Edinburgh, University of Oxford"
   },
   {
      "surname": "Gilbert",
      "awards": 1,
      "education": "University of Cincinnati"
   },
   {
      "surname": "Giles",
      "awards": 7,
      "education": "Rhodes College, University of Tennessee, University of Michigan, University of Arizona"
   },
   {
      "surname": "Ginsburg",
      "awards": 0,
      "education": "City College of New York, University of Michigan"
   },
   {
      "surname": "Glass",
      "awards": 0,
      "education": "Cornell University"
   },
   {
      "surname": "Gödel",
      "awards": 3,
      "education": "Cornell University"
   },
   {
      "surname": "Goel",
      "awards": 1,
      "education": "Ohio State University"
   },
   {
      "surname": "Goguen",
      "awards": 0,
      "education": "Harvard University, University of California"
   },
   {
      "surname": "Gold",
      "awards": 0,
      "education": "California Institute of Technology, Princeton University"
   },
   {
      "surname": "Goldberg",
      "awards": 0,
      "education": "University of Michigan, University of Chicago"
   },
   {
      "surname": "Goldberg",
      "awards": 2,
      "education": "Massachusetts Institute of Technology"
   },
   {
      "surname": "Goldberg",
      "awards": 0,
      "education": "University of Toronto Schools, University of Waterloo, University of California"
   },
   {
      "surname": "Anne",
      "awards": 0,
      "education": "Princeton University, University of Wisconsin–Madison"
   },
   {
      "surname": "Goldreich",
      "awards": 1,
      "education": "Weizmann Institute"
   },
   {
      "surname": "Goldwasser",
      "awards": 3,
      "education": "Carnegie Mellon"
   },
   {
      "surname": "Golub",
      "awards": 0,
      "education": "University of Illinois"
   },
   {
      "surname": "Golumbic",
      "awards": 0,
      "education": "Pennsylvania State University, Columbia University"
   },
   {
      "surname": "Gonnet",
      "awards": 1,
      "education": "University of Waterloo"
   },
   {
      "surname": "Goodfellow",
      "awards": 0,
      "education": "Stanford University"
   },
   {
      "surname": "Gosling",
      "awards": 6,
      "education": "University of Calgary, Carnegie Mellon University"
   },
   {
      "surname": "Graham",
      "awards": 0,
      "education": "Cornell University"
   },
   {
      "surname": "Graham",
      "awards": 0,
      "education": "University of Massachusetts"
   },
   {
      "surname": "Graham",
      "awards": 5,
      "education": "Harvard University, University of California"
   },
   {
      "surname": "Gray",
      "awards": 2,
      "education": "University of California"
   },
   {
      "surname": "Greibach",
      "awards": 0,
      "education": "Radcliffe College, Harvard University"
   },
   {
      "surname": "Gries",
      "awards": 10,
      "education": "University of Illinois, Technical University of Munich"
   },
   {
      "surname": "Griesemer",
      "awards": 0,
      "education": "University of California"
   },
   {
      "surname": "Griswold",
      "awards": 0,
      "education": "University of California"
   },
   {
      "surname": "Gropp",
      "awards": 2,
      "education": "Stanford University"
   },
   {
      "surname": "Gruber",
      "awards": 0,
      "education": "Loyola University, University of Massachusetts"
   },
   {
      "surname": "Guberman",
      "awards": 0,
      "education": "Institute of Electrical Communications Odessa"
   },
   {
      "surname": "Guha",
      "awards": 2,
      "education": "Indian Institute of Technology Madras, University of California, Stanford University"
   },
   {
      "surname": "Gunther",
      "awards": 9,
      "education": "La Trobe University, University of Southampton"
   },
   {
      "surname": "Gutknecht",
      "awards": 0,
      "education": "ETH Zurich"
   },
   {
      "surname": "Guy",
      "awards": 0,
      "education": "University of California"
   },
   {
      "surname": "Habermann",
      "awards": 0,
      "education": "Free University of Amsterdam, Eindhoven University of Technology"
   },
   {
      "surname": "Hahn",
      "awards": 0,
      "education": "Eindhoven University of Technology"
   },
   {
      "surname": "Hall",
      "awards": 1,
      "education": "University of Washington, Rutgers University, Eastern Nazarene College, Boston University, Massachusetts Institute of Technology, Harvard University"
   },
   {
      "surname": "Hall",
      "awards": 1,
      "education": "University of Southampton, City University London"
   },
   {
      "surname": "Halpern",
      "awards": 3,
      "education": "University of Toronto, Harvard University"
   },
   {
      "surname": "Hamilton",
      "awards": 10,
      "education": "University of Michigan, Earlham College"
   },
   {
      "surname": "Hamming",
      "awards": 7,
      "education": "University of Chicago, University of Nebraska, University of Illinois"
   },
   {
      "surname": "Han",
      "awards": 0,
      "education": "University of Wisconsin"
   },
   {
      "surname": "Harary",
      "awards": 0,
      "education": "Brooklyn College, University of California"
   },
   {
      "surname": "Harris",
      "awards": 0,
      "education": "American University in Cairo"
   },
   {
      "surname": "Hartmanis",
      "awards": 13,
      "education": "University of Marburg, University of Kansas City"
   },
   {
      "surname": "Håstad",
      "awards": 4,
      "education": "Massachusetts Institute of Technology, Uppsala University, Stockholm University"
   },
   {
      "surname": "Hatton",
      "awards": 1,
      "education": "King's College"
   },
   {
      "surname": "Hawryszkiewycz",
      "awards": 0,
      "education": "Massachusetts Institute of Technology"
   },
   {
      "surname": "Jifeng",
      "awards": 0,
      "education": "Fudan University"
   },
   {
      "surname": "Hehner",
      "awards": 0,
      "education": "Carleton University, University of Toronto"
   },
   {
      "surname": "Hellman",
      "awards": 9,
      "education": "New York University, Stanford University"
   },
   {
      "surname": "Heiser",
      "awards": 14,
      "education": "University of Freiburg, Brock University, ETH Zurich"
   },
   {
      "surname": "Hendler",
      "awards": 0,
      "education": "Brown University, Southern Methodist University"
   },
   {
      "surname": "Hennessy",
      "awards": 6,
      "education": "New York University"
   },
   {
      "surname": "Herbert",
      "awards": 0,
      "education": "Leeds University, Cambridge University"
   },
   {
      "surname": "Hewitt",
      "awards": 0,
      "education": "Massachusetts Institute of Technology"
   },
   {
      "surname": "Hightower",
      "awards": 0,
      "education": "Clayton State University"
   },
   {
      "surname": "Hillis",
      "awards": 2,
      "education": "Massachusetts Institute of Technology"
   },
   {
      "surname": "Hinton",
      "awards": 9,
      "education": "Clifton College"
   },
   {
      "surname": "Hirschberg",
      "awards": 6,
      "education": "University of Pennsylvania, University of Michigan"
   },
   {
      "surname": "Ho",
      "awards": 7,
      "education": "Chinese Universit, State University of New York"
   },
   {
      "surname": "Hoare",
      "awards": 21,
      "education": "Merton College, University of Oxford"
   },
   {
      "surname": "Hodes",
      "awards": 0,
      "education": "Polytechnic Institute of Brooklyn"
   },
   {
      "surname": "Holberton",
      "awards": 4,
      "education": "Massachusetts Institute of Technology"
   },
   {
      "surname": "Holland",
      "awards": 3,
      "education": "University of Michigan"
   },
   {
      "surname": "Hollerith",
      "awards": 3,
      "education": "City College of New York, Columbia University"
   },
   {
      "surname": "Holzmann",
      "awards": 1,
      "education": "Delft University of Technology"
   },
   {
      "surname": "Hopcroft",
      "awards": 7,
      "education": "Seattle University, Stanford University"
   },
   {
      "surname": "Hopper",
      "awards": 27,
      "education": "Massachusetts Institute of Technology"
   },
   {
      "surname": "Horvitz",
      "awards": 0,
      "education": "Stanford University"
   },
   {
      "surname": "Householder",
      "awards": 0,
      "education": "University of Chicago"
   },
   {
      "surname": "Hudak",
      "awards": 6,
      "education": "Vanderbilt University, Massachusetts Institute of Technology"
   },
   {
      "surname": "Huffman",
      "awards": 5,
      "education": "Ohio State University, Massachusetts Institute of Technology"
   },
   {
      "surname": "Hughes",
      "awards": 1,
      "education": "University of Oxford"
   },
   {
      "surname": "Hui",
      "awards": 1,
      "education": "Massachusetts Institute of Technology"
   },
   {
      "surname": "Humphrey",
      "awards": 1,
      "education": "University of Chicago, Illinois Institute of Technology"
   },
   {
      "surname": "Hutchins",
      "awards": 0,
      "education": "University of California"
   },
   {
      "surname": "Hoberman",
      "awards": 0,
      "education": "Queens College"
   },
   {
      "surname": "Ichbiah",
      "awards": 3,
      "education": "Massachusetts Institute of Technology"
   },
   {
      "surname": "Ierusalimschy",
      "awards": 0,
      "education": "University of Rio de Janeiro"
   },
   {
      "surname": "Ingalls",
      "awards": 2,
      "education": "Harvard University"
   },
   {
      "surname": "Irwin",
      "awards": 3,
      "education": "University of Illinois, Memphis State University"
   },
   {
      "surname": "Iverson",
      "awards": 6,
      "education": "Massachusetts Institute of Technology"
   },
   {
      "surname": "Jacobson",
      "awards": 0,
      "education": "Chalmers Institute of Technology, Royal Institute of Technology"
   },
   {
      "surname": "Jain",
      "awards": 10,
      "education": "Indian Institute of Technology, Ohio State University"
   },
   {
      "surname": "Jain",
      "awards": 0,
      "education": "Indian Institute of Technology"
   },
   {
      "surname": "James",
      "awards": 0,
      "education": "Massachusetts Institute of Technology"
   },
   {
      "surname": "Johnson",
      "awards": 2,
      "education": "Amherst College, Massachusetts Institute of Technology"
   },
   {
      "surname": "Johnson",
      "awards": 0,
      "education": "University of Illinois"
   },
   {
      "surname": "Jones",
      "awards": 0,
      "education": "University of Oxford"
   },
   {
      "surname": "Jordan",
      "awards": 5,
      "education": "Louisiana State University, Arizona State University"
   },
   {
      "surname": "Joseph",
      "awards": 1,
      "education": "Wilson College, Welsh College of Advanced Technology, Churchill College"
   },
   {
      "surname": "Joshi",
      "awards": 12,
      "education": "College of Engineering, Indian Institute of Science, University of Pennsylvania"
   },
   {
      "surname": "Joy",
      "awards": 4,
      "education": "University of Michigan, University of California"
   },
   {
      "surname": "Jurafsky",
      "awards": 2,
      "education": "University of California"
   },
   {
      "surname": "Kahan",
      "awards": 4,
      "education": "University of Toronto"
   },
   {
      "surname": "Kahn",
      "awards": 2,
      "education": "City College of New York, Princeton University"
   },
   {
      "surname": "Kak",
      "awards": 0,
      "education": "University of Madras, Indian Institute of Technology"
   },
   {
      "surname": "Kamp",
      "awards": 0,
      "education": "University of Illinois"
   },
   {
      "surname": "Karger",
      "awards": 1,
      "education": "Harvard University, Stanford University"
   },
   {
      "surname": "Karp",
      "awards": 10,
      "education": "Harvard University"
   },
   {
      "surname": "Karmarkar",
      "awards": 11,
      "education": "University of California"
   },
   {
      "surname": "Karpinski",
      "awards": 0,
      "education": "University of Illinois"
   },
   {
      "surname": "Kaehler",
      "awards": 0,
      "education": "Stanford University, Carnegie Mellon University"
   },
   {
      "surname": "Kay",
      "awards": 6,
      "education": "University of Colorado at Boulder, University of Utah College of Engineering"
   },
   {
      "surname": "Kayal",
      "awards": 6,
      "education": "University of Illinois"
   },
   {
      "surname": "Kellis",
      "awards": 3,
      "education": "Massachusetts Institute of Technology"
   },
   {
      "surname": "Kemeny",
      "awards": 0,
      "education": "Princeton University"
   },
   {
      "surname": "Kennedy",
      "awards": 0,
      "education": "Rice University, New York University"
   },
   {
      "surname": "Kernighan",
      "awards": 0,
      "education": "Princeton University"
   },
   {
      "surname": "Kesselman",
      "awards": 0,
      "education": "University of Southern California"
   },
   {
      "surname": "Kiczales",
      "awards": 0,
      "education": "Massachusetts Institute of Technology"
   },
   {
      "surname": "Kirstein",
      "awards": 8,
      "education": "Massachusetts Institute of Technology"
   },
   {
      "surname": "Kleene",
      "awards": 2,
      "education": "Amherst College, Princeton University"
   },
   {
      "surname": "Klein",
      "awards": 4,
      "education": "Cornell University, University of Oxford, Stanford University"
   },
   {
      "surname": "Kleinrock",
      "awards": 5,
      "education": "City College of New York, Massachusetts Institute of Technology"
   },
   {
      "surname": "Knuth",
      "awards": 17,
      "education": "Case Institute of Technology, California Institute of Technology"
   },
   {
      "surname": "Koenig",
      "awards": 0,
      "education": "Columbia University"
   },
   {
      "surname": "Koller",
      "awards": 5,
      "education": "Hebrew University of Jerusalem"
   },
   {
      "surname": "Kölling",
      "awards": 8,
      "education": "University of Bremen, University of Sydney"
   },
   {
      "surname": "Kolmogorov",
      "awards": 11,
      "education": "Moscow State University"
   },
   {
      "surname": "Kolodner",
      "awards": 1,
      "education": "Brandeis University, Yale University"
   },
   {
      "surname": "Korn",
      "awards": 0,
      "education": "Rensselaer Polytechnic Institute"
   },
   {
      "surname": "Antonius",
      "awards": 0,
      "education": "University of Amsterdam"
   },
   {
      "surname": "Kowalski",
      "awards": 1,
      "education": "University of Chicago, University of Bridgeport, Stanford University, University of Warsaw"
   },
   {
      "surname": "Koza",
      "awards": 0,
      "education": "Stanford University"
   },
   {
      "surname": "Krogstie",
      "awards": 0,
      "education": "Norwegian University of Science and Technology"
   },
   {
      "surname": "Kruskal",
      "awards": 0,
      "education": "University of Chicago"
   },
   {
      "surname": "Kruusmaa",
      "awards": 0,
      "education": "Tallinn University of Technology, Chalmers University of Technology"
   },
   {
      "surname": "Kurtz",
      "awards": 2,
      "education": "University of California"
   },
   {
      "surname": "Ladner",
      "awards": 5,
      "education": "St. Mary's College, University of California"
   },
   {
      "surname": "Lam",
      "awards": 9,
      "education": "Carnegie Mellon University"
   },
   {
      "surname": "Lamport",
      "awards": 6,
      "education": "Massachusetts Institute of Technology"
   },
   {
      "surname": "Lampson",
      "awards": 6,
      "education": "Harvard University, University of California"
   },
   {
      "surname": "Landin",
      "awards": 0,
      "education": "Clare College, Cambridge University"
   },
   {
      "surname": "Lane",
      "awards": 0,
      "education": "Carnegie Mellon University"
   },
   {
      "surname": "Langefors",
      "awards": 0,
      "education": "Royal Institute of Technology"
   },
   {
      "surname": "Lattner",
      "awards": 2,
      "education": "University of Portland"
   },
   {
      "surname": "Lawrence",
      "awards": 8,
      "education": "Massachusetts Institute of Technology"
   },
   {
      "surname": "Lazowska",
      "awards": 0,
      "education": "Brown University, University of Toronto"
   },
   {
      "surname": "Lederberg",
      "awards": 3,
      "education": "Columbia University"
   },
   {
      "surname": "Lehman,",
      "awards": 3,
      "education": "Imperial College London"
   },
   {
      "surname": "Leiserson",
      "awards": 8,
      "education": "Yale University"
   },
   {
      "surname": "Lenat",
      "awards": 1,
      "education": "Yale University"
   },
   {
      "surname": "LeCun",
      "awards": 3,
      "education": "Sorbonne University"
   },
   {
      "surname": "Lerdorf",
      "awards": 0,
      "education": "University of Waterloo"
   },
   {
      "surname": "Rafailovych",
      "awards": 0,
      "education": "University of Illinois"
   },
   {
      "surname": "Levin",
      "awards": 1,
      "education": "Moscow University, Massachusetts Institute of Technology"
   },
   {
      "surname": "Leyton-Brown",
      "awards": 1,
      "education": "McMaster University, Stanford University"
   },
   {
      "surname": "Licklider",
      "awards": 0,
      "education": "Washington University, University of Rochester"
   },
   {
      "surname": "Liddle",
      "awards": 0,
      "education": "Stanford University"
   },
   {
      "surname": "Liedtke",
      "awards": 0,
      "education": "Bielefeld University, Technical University of Berlin"
   },
   {
      "surname": "Lions",
      "awards": 0,
      "education": "University of Sydney, University of Cambridge"
   },
   {
      "surname": "Lindsey",
      "awards": 0,
      "education": "Yale University"
   },
   {
      "surname": "Lipton",
      "awards": 4,
      "education": "Carnegie Mellon"
   },
   {
      "surname": "Liskov",
      "awards": 3,
      "education": "University of California"
   },
   {
      "surname": "Liu",
      "awards": 0,
      "education": "Peking University"
   },
   {
      "surname": "Long",
      "awards": 2,
      "education": "San Diego State University, University of California"
   },
   {
      "surname": "Lopez",
      "awards": 7,
      "education": "New Mexico State University"
   },
   {
      "surname": "Lovegrove",
      "awards": 0,
      "education": "Newnham College, Cambridge University"
   },
   {
      "surname": "Lovelace",
      "awards": 0,
      "education": "Yale University"
   },
   {
      "surname": "Luckham",
      "awards": 0,
      "education": "Massachusetts Institute of Technology"
   },
   {
      "surname": "Luks",
      "awards": 2,
      "education": "City College of New York"
   },
   {
      "surname": "Lynch",
      "awards": 7,
      "education": "Brooklyn College, Massachusetts Institute of Technology"
   },
   {
      "surname": "Thalmann",
      "awards": 5,
      "education": "University of Geneva, École Polytechnique Fédérale de Lausanne"
   },
   {
      "surname": "Maibaum",
      "awards": 1,
      "education": "University of Toronto, University of London"
   },
   {
      "surname": "Marlow",
      "awards": 1,
      "education": "University of Glasgow, University of Bristol"
   },
   {
      "surname": "Manna",
      "awards": 4,
      "education": "Israel Institute of Technology, Carnegie Mellon University"
   },
   {
      "surname": "Martin",
      "awards": 1,
      "education": "University of Oxford"
   },
   {
      "surname": "Martin",
      "awards": 0,
      "education": "Massachusetts Institute of Technology"
   },
   {
      "surname": "Mashey",
      "awards": 0,
      "education": "Pennsylvania State University"
   },
   {
      "surname": "Matiyasevich",
      "awards": 7,
      "education": "Leningrad State University"
   },
   {
      "surname": "Matsumoto",
      "awards": 0,
      "education": "University of Tsukuba, Shimane University"
   },
   {
      "surname": "Mauchly",
      "awards": 3,
      "education": "Johns Hopkins University"
   },
   {
      "surname": "Maulik",
      "awards": 11,
      "education": "University of Calcutta"
   },
   {
      "surname": "McAuley",
      "awards": 1,
      "education": "University of Cambridge"
   },
   {
      "surname": "McBride",
      "awards": 0,
      "education": "University of Edinburgh"
   },
   {
      "surname": "McCarthy",
      "awards": 7,
      "education": "Massachusetts Institute of Technology"
   },
   {
      "surname": "McCallum",
      "awards": 1,
      "education": "Dartmouth College, University of Rochester"
   },
   {
      "surname": "McIlroy",
      "awards": 3,
      "education": "Cornell University, Massachusetts Institute of Technology"
   },
   {
      "surname": "McKinstry",
      "awards": 0,
      "education": "University of Oxford"
   },
   {
      "surname": "McKusick",
      "awards": 0,
      "education": "University of California"
   },
   {
      "surname": "Meertens",
      "awards": 2,
      "education": "University of Oxford"
   },
   {
      "surname": "Mehlhorn",
      "awards": 4,
      "education": "Technical University of Munich"
   },
   {
      "surname": "Metcalf",
      "awards": 0,
      "education": "University of Oxford"
   },
   {
      "surname": "Meyer",
      "awards": 10,
      "education": "École Polytechnique, Stanford University"
   },
   {
      "surname": "Micali",
      "awards": 3,
      "education": "La Sapienza University"
   },
   {
      "surname": "Milner",
      "awards": 5,
      "education": "Eton College, Swansea University, Stanford University"
   },
   {
      "surname": "Minker",
      "awards": 2,
      "education": "Brooklyn College"
   },
   {
      "surname": "Minsky",
      "awards": 5,
      "education": "Harvard University"
   },
   {
      "surname": "Mitchell",
      "awards": 1,
      "education": "University of Waterloo, Carnegie Mellon University"
   },
   {
      "surname": "Mitchell",
      "awards": 1,
      "education": "Massachusetts Institute of Technology, Stanford University"
   },
   {
      "surname": "Arvind",
      "awards": 7,
      "education": "University of Minnesota"
   },
   {
      "surname": "Mockapetris",
      "awards": 10,
      "education": "Massachusetts Institute of Technology, University of California"
   },
   {
      "surname": "Moler",
      "awards": 2,
      "education": "California Institute of Technology, Stanford University"
   },
   {
      "surname": "Moller",
      "awards": 0,
      "education": "University of British Columbia, University of Waterloo, University of Edinburgh"
   },
   {
      "surname": "Moon",
      "awards": 0,
      "education": "New York University"
   },
   {
      "surname": "Moore",
      "awards": 0,
      "education": "Massachusetts Institute of Technology, Stanford University"
   },
   {
      "surname": "Moore",
      "awards": 0,
      "education": "Virginia Tech, Brown University"
   },
   {
      "surname": "Moore",
      "awards": 9,
      "education": "San José State University, University of California"
   },
   {
      "surname": "Moore",
      "awards": 0,
      "education": "Massachusetts Institute of Technology, University of Edinburgh"
   },
   {
      "surname": "Moore",
      "awards": 4,
      "education": "Stanford University"
   },
   {
      "surname": "Moravec",
      "awards": 0,
      "education": "Acadia University, University of Western Ontario, Stanford University"
   },
   {
      "surname": "Morgan",
      "awards": 0,
      "education": "University of Sydney"
   },
   {
      "surname": "Morris",
      "awards": 0,
      "education": "Harvard University , Cornell University"
   },
   {
      "surname": "Moses",
      "awards": 0,
      "education": "Columbia University"
   },
   {
      "surname": "Motwani",
      "awards": 7,
      "education": "Indian Institute of Technology, University of California"
   },
   {
      "surname": "Mukhanov",
      "awards": 0,
      "education": "Moscow Engineering Physics Institute, Moscow State University"
   },
   {
      "surname": "Muggleton",
      "awards": 4,
      "education": "University of Edinburgh"
   },
   {
      "surname": "Müller",
      "awards": 1,
      "education": "University of Karlsruhe"
   },
   {
      "surname": "Mycroft",
      "awards": 0,
      "education": "University of Oxford"
   },
   {
      "surname": "Myers",
      "awards": 1,
      "education": "University of Toronto"
   },
   {
      "surname": "Nadin",
      "awards": 0,
      "education": "Illinois Institute of Technology, University of Oregon, Hadassah University"
   },
   {
      "surname": "Nagao",
      "awards": 1,
      "education": "Kyoto University"
   },
   {
      "surname": "Nake",
      "awards": 2,
      "education": "University of Stuttgart"
   },
   {
      "surname": "Nardi",
      "awards": 0,
      "education": "University of Oxford"
   },
   {
      "surname": "Naur",
      "awards": 2,
      "education": "Niels Bohr Institute, Technical University of Copenhagen, University of Copenhagen"
   },
   {
      "surname": "Needham",
      "awards": 1,
      "education": "St John's College"
   },
   {
      "surname": "Nell",
      "awards": 0,
      "education": "Drexel University, Bowling Green State University"
   },
   {
      "surname": "Nelson",
      "awards": 1,
      "education": "Harvard University, Stanford University"
   },
   {
      "surname": "Neumann",
      "awards": 0,
      "education": "Bowling Green State University"
   },
   {
      "surname": "Neumann",
      "awards": 0,
      "education": "St John's College"
   },
   {
      "surname": "Neumann",
      "awards": 0,
      "education": "St John's College"
   },
   {
      "surname": "Newell",
      "awards": 21,
      "education": "Stanford University, Princeton University, Carnegie Mellon University"
   },
   {
      "surname": "Newman",
      "awards": 3,
      "education": "St John's College"
   },
   {
      "surname": "Ng",
      "awards": 9,
      "education": "Stanford University"
   },
   {
      "surname": "Nilsson",
      "awards": 1,
      "education": "Stanford University"
   },
   {
      "surname": "Nijssen",
      "awards": 0,
      "education": "Eindhoven University of Technology"
   },
   {
      "surname": "Nipkow",
      "awards": 0,
      "education": "Technische Hochschule Darmstadt, University of Manchester"
   },
   {
      "surname": "Nivat",
      "awards": 7,
      "education": "Blaise Pascal Institute"
   },
   {
      "surname": "Nkambule",
      "awards": 3,
      "education": "University of Pretoria, Cefups Academy"
   },
   {
      "surname": "Noe",
      "awards": 0,
      "education": "University of California, Stanford University"
   },
   {
      "surname": "Nordin",
      "awards": 0,
      "education": "University of Dortmund, Chalmers University of Technology, Göteborg University"
   },
   {
      "surname": "Norman",
      "awards": 7,
      "education": "Massachusetts Institute of Technology, University of Pennsylvania"
   },
   {
      "surname": "Norvig",
      "awards": 2,
      "education": "Brown University, University of California"
   },
   {
      "surname": "Novacky",
      "awards": 0,
      "education": "Wheeling Jesuit College, University of Pittsburgh"
   },
   {
      "surname": "Nygaard",
      "awards": 4,
      "education": "University of Oslo"
   },
   {
      "surname": "Odersky",
      "awards": 0,
      "education": "Ludwig Maximilian Universit, ETH Zurich"
   },
   {
      "surname": "O'Hearn",
      "awards": 1,
      "education": "Dalhousie University"
   },
   {
      "surname": "Olle",
      "awards": 0,
      "education": "University of Manchester"
   },
   {
      "surname": "Omohundro",
      "awards": 0,
      "education": "Stanford University, University of California"
   },
   {
      "surname": "Ornstein",
      "awards": 0,
      "education": "Massachusetts Institute of Technology"
   },
   {
      "surname": "O'Sullivan",
      "awards": 2,
      "education": "University of Sydney"
   },
   {
      "surname": "Ousterhout",
      "awards": 2,
      "education": "Massachusetts Institute of Technology"
   },
   {
      "surname": "Overmars",
      "awards": 0,
      "education": "Utrecht University"
   },
   {
      "surname": "Owicki",
      "awards": 0,
      "education": "Cornell University"
   },
   {
      "surname": "Page",
      "awards": 9,
      "education": "Massachusetts Institute of Technology"
   },
   {
      "surname": "Pal",
      "awards": 1,
      "education": "University of Calcutta"
   },
   {
      "surname": "Pandya",
      "awards": 1,
      "education": "Cornell University"
   },
   {
      "surname": "Papadimitriou",
      "awards": 5,
      "education": "National Technical University of Athens, Princeton University"
   },
   {
      "surname": "Park",
      "awards": 0,
      "education": "University of Oxford, Massachusetts Institute of Technology"
   },
   {
      "surname": "Parnas",
      "awards": 0,
      "education": "Carnegie Mellon University"
   },
   {
      "surname": "Dhanurjay",
      "awards": 0,
      "education": "Earl Warren College, University of California, Maryland College of Computer"
   },
   {
      "surname": "Patt",
      "awards": 6,
      "education": "University of Texas"
   },
   {
      "surname": "Patterson",
      "awards": 3,
      "education": "University of California"
   },
   {
      "surname": "Paterson",
      "awards": 2,
      "education": "University of Cambridge"
   },
   {
      "surname": "Pătrașcu",
      "awards": 0,
      "education": "Massachusetts Institute of Technology"
   },
   {
      "surname": "Paulson",
      "awards": 1,
      "education": "California Institute of Technology, Stanford University"
   },
   {
      "surname": "Pausch",
      "awards": 5,
      "education": "Brown University, Carnegie Mellon University"
   },
   {
      "surname": "Pavón",
      "awards": 0,
      "education": "Technical University of Madrid, Université Pierre et Marie Curie"
   },
   {
      "surname": "Pearl",
      "awards": 43,
      "education": "Israel Institute of Technology, New Jersey Institute of Technology, Rutgers University, New York University"
   },
   {
      "surname": "Perlis",
      "awards": 2,
      "education": "Carnegie Mellon, Massachusetts Institute of Technology"
   },
   {
      "surname": "Perlman",
      "awards": 11,
      "education": "Massachusetts Institute of Technology"
   },
   {
      "surname": "Perotto",
      "awards": 0,
      "education": "Turin Polytechnic"
   },
   {
      "surname": "Péter",
      "awards": 0,
      "education": "Eötvös Loránd University"
   },
   {
      "surname": "Jones",
      "awards": 1,
      "education": "University of Cambridge, Trinity College"
   },
   {
      "surname": "Pham",
      "awards": 0,
      "education": "Massachusetts Institute of Technology"
   },
   {
      "surname": "Pieraccini",
      "awards": 0,
      "education": "University of Pisa"
   },
   {
      "surname": "Pingali",
      "awards": 10,
      "education": "Massachusetts Institute of Technology"
   },
   {
      "surname": "Plotkin",
      "awards": 3,
      "education": "University of Glasgow, University of Edinburgh"
   },
   {
      "surname": "Pnueli",
      "awards": 6,
      "education": "Weizmann Institute of Science, Stanford University"
   },
   {
      "surname": "Poel",
      "awards": 1,
      "education": "Delft University of Technology, University of Amsterdam"
   },
   {
      "surname": "Williams",
      "awards": 0,
      "education": "Massachusetts Institute of Technology"
   },
   {
      "surname": "Post",
      "awards": 0,
      "education": "City College of New York, Columbia University"
   },
   {
      "surname": "Postel",
      "awards": 1,
      "education": "University of California"
   },
   {
      "surname": "Preparata",
      "awards": 2,
      "education": "University of Rome"
   },
   {
      "surname": "Press",
      "awards": 0,
      "education": "Harvard University, California Institute of Technology"
   },
   {
      "surname": "Rabana",
      "awards": 0,
      "education": "University of Cape Town"
   },
   {
      "surname": "Rozenberg",
      "awards": 11,
      "education": "Warsaw University of Technology"
   },
   {
      "surname": "Rabin",
      "awards": 10,
      "education": "Hebrew University of Jerusalem, University of Pennsylvania, Princeton University"
   },
   {
      "surname": "Radev",
      "awards": 5,
      "education": "Yale University"
   },
   {
      "surname": "Raman",
      "awards": 1,
      "education": "Massachusetts Institute of Technology"
   },
   {
      "surname": "Randell",
      "awards": 0,
      "education": "Imperial College London"
   },
   {
      "surname": "Ravn",
      "awards": 2,
      "education": "University of Copenhagen, Technical University of Denmark"
   },
   {
      "surname": "Reddy",
      "awards": 6,
      "education": "Massachusetts Institute of Technology"
   },
   {
      "surname": "Reed",
      "awards": 0,
      "education": "Massachusetts Institute of Technology"
   },
   {
      "surname": "Reenskaug",
      "awards": 0,
      "education": "Imperial College London"
   },
   {
      "surname": "Reynolds",
      "awards": 1,
      "education": "Purdue University, Harvard University"
   },
   {
      "surname": "Reynolds",
      "awards": 0,
      "education": "University of Southern California"
   },
   {
      "surname": "Riet",
      "awards": 0,
      "education": "University of Amsterdam"
   },
   {
      "surname": "Richards",
      "awards": 0,
      "education": "University of Manchester"
   },
   {
      "surname": "Richards",
      "awards": 1,
      "education": "University of Cambridge"
   },
   {
      "surname": "Ries",
      "awards": 0,
      "education": "Imperial College London"
   },
   {
      "surname": "Rijsbergen",
      "awards": 5,
      "education": "University of Western Australia, University of Cambridge"
   },
   {
      "surname": "Ritchie",
      "awards": 8,
      "education": "Harvard University"
   },
   {
      "surname": "Rivest",
      "awards": 5,
      "education": "Yale University, Stanford Universityσ"
   },
   {
      "surname": "Robinson",
      "awards": 1,
      "education": "University of Sydney"
   },
   {
      "surname": "Rolland",
      "awards": 0,
      "education": "University of Paris"
   },
   {
      "surname": "Romero",
      "awards": 0,
      "education": "Imperial College London"
   },
   {
      "surname": "Rosenfeld",
      "awards": 3,
      "education": "University of Maryland, Columbia University"
   },
   {
      "surname": "Taylor",
      "awards": 3,
      "education": "Oberlin College, Massachusetts Institute of Technology"
   },
   {
      "surname": "Rossum",
      "awards": 6,
      "education": "University of Amsterdam"
   },
   {
      "surname": "Rothman",
      "awards": 0,
      "education": "Imperial College London"
   },
   {
      "surname": "Royce",
      "awards": 0,
      "education": "California Institute of Technology"
   },
   {
      "surname": "Rucker",
      "awards": 0,
      "education": "Swarthmore College, Rutgers University"
   },
   {
      "surname": "Rudich",
      "awards": 1,
      "education": "Imperial College London"
   },
   {
      "surname": "Rulifson",
      "awards": 3,
      "education": "University of Washington"
   },
   {
      "surname": "Rumbaugh",
      "awards": 0,
      "education": "Massachusetts Institute of Technology, California Institute of Technology"
   },
   {
      "surname": "Ružička",
      "awards": 1,
      "education": "Comenius University"
   },
   {
      "surname": "Sadowsky",
      "awards": 0,
      "education": "Harvard University"
   },
   {
      "surname": "Sadrzadeh",
      "awards": 0,
      "education": "Sharif University of Technology"
   },
   {
      "surname": "Saif",
      "awards": 0,
      "education": "Massachusetts Institute of Technology"
   },
   {
      "surname": "Salton",
      "awards": 0,
      "education": "Brooklyn College"
   },
   {
      "surname": "Sammet",
      "awards": 7,
      "education": "Mount Holyoke College, University of Illinois"
   },
   {
      "surname": "Sammut",
      "awards": 0,
      "education": "Massachusetts Institute of Technology"
   },
   {
      "surname": "Sassenrath",
      "awards": 0,
      "education": "University of California"
   },
   {
      "surname": "Satyanarayanan",
      "awards": 5,
      "education": "Indian Institute of Technology"
   },
   {
      "surname": "Savitch",
      "awards": 0,
      "education": "University of California"
   },
   {
      "surname": "Schaeffer",
      "awards": 2,
      "education": "University of Waterloo"
   },
   {
      "surname": "Schickard",
      "awards": 0,
      "education": "University of Tübingen"
   },
   {
      "surname": "Schmidhuber",
      "awards": 0,
      "education": "Technical University of Munich"
   },
   {
      "surname": "Schneider",
      "awards": 0,
      "education": "University of Oxford"
   },
   {
      "surname": "Schneier",
      "awards": 0,
      "education": "American University, University of Rochester"
   },
   {
      "surname": "Schneider",
      "awards": 14,
      "education": "Stony Brook University"
   },
   {
      "surname": "Schoenebeck",
      "awards": 6,
      "education": "Massachusetts Institute of Technology"
   },
   {
      "surname": "Schroeder",
      "awards": 0,
      "education": "Massachusetts Institute of Technology"
   },
   {
      "surname": "Schölkopf",
      "awards": 10,
      "education": "University of London"
   },
   {
      "surname": "Scott",
      "awards": 6,
      "education": "Princeton University"
   },
   {
      "surname": "Scott",
      "awards": 0,
      "education": "University of Wisconsin–Madison"
   },
   {
      "surname": "Sedgewick",
      "awards": 3,
      "education": "Stanford University"
   },
   {
      "surname": "Sethi",
      "awards": 0,
      "education": "Indian Institute of Technology, Princeton University"
   },
   {
      "surname": "Shadbolt",
      "awards": 11,
      "education": "Newcastle University, University of Edinburgh"
   },
   {
      "surname": "Shamir",
      "awards": 11,
      "education": "Tel Aviv University, Weizmann Institute of Science"
   },
   {
      "surname": "Shannon",
      "awards": 15,
      "education": "University of Michigan, Massachusetts Institute of Technology"
   },
   {
      "surname": "Shaw",
      "awards": 0,
      "education": "University of California"
   },
   {
      "surname": "Shaw",
      "awards": 0,
      "education": "Massachusetts Institute of Technology"
   },
   {
      "surname": "Shenker",
      "awards": 5,
      "education": "Brown University, University of Chicago"
   },
   {
      "surname": "Shekhar",
      "awards": 10,
      "education": "University of California"
   },
   {
      "surname": "Shneiderman",
      "awards": 1,
      "education": "University of New York"
   },
   {
      "surname": "Shortliffe",
      "awards": 0,
      "education": "Harvard University, Stanford University"
   },
   {
      "surname": "Siewiorek",
      "awards": 4,
      "education": "University of Michigan"
   },
   {
      "surname": "Sifakis",
      "awards": 10,
      "education": "National Technical University of Athens, University of Grenoble"
   },
   {
      "surname": "Simon",
      "awards": 4,
      "education": "Technische Hochschule Darmstadt"
   },
   {
      "surname": "Singh",
      "awards": 5,
      "education": "Indian Institute of Technology Delhi, University of Texas"
   },
   {
      "surname": "Sitaraman",
      "awards": 0,
      "education": "Indian Institute of Technology, Princeton University"
   },
   {
      "surname": "Sleator",
      "awards": 1,
      "education": "University of Illinois, Stanford University"
   },
   {
      "surname": "Sloman",
      "awards": 0,
      "education": "University of Cape Town"
   },
   {
      "surname": "Sølvberg",
      "awards": 0,
      "education": "Norwegian Institute of Technology"
   },
   {
      "surname": "Smith",
      "awards": 0,
      "education": "Massachusetts Institute of Technology"
   },
   {
      "surname": "Smith",
      "awards": 1,
      "education": "Oberlin College, Stanford University"
   },
   {
      "surname": "Spewak",
      "awards": 0,
      "education": "Case Western Reserve University, University of Michigan"
   },
   {
      "surname": "Spradling",
      "awards": 0,
      "education": "University of Nebraska"
   },
   {
      "surname": "Sproull",
      "awards": 0,
      "education": "Deep Springs College, Cornell University"
   },
   {
      "surname": "Srihari",
      "awards": 0,
      "education": "University of Waterloo, University of Buffalo"
   },
   {
      "surname": "Srihari",
      "awards": 3,
      "education": "National College of Bangalore University"
   },
   {
      "surname": "Stachowiak",
      "awards": 0,
      "education": "Massachusetts Institute of Technology"
   },
   {
      "surname": "Stallman",
      "awards": 5,
      "education": "Harvard University, Massachusetts Institute of Technology"
   },
   {
      "surname": "Stamper",
      "awards": 0,
      "education": "Oxford University"
   },
   {
      "surname": "Starner",
      "awards": 0,
      "education": "Massachusetts Institute of Technology"
   },
   {
      "surname": "Stearns",
      "awards": 2,
      "education": "Carleton College, Princeton University"
   },
   {
      "surname": "Steele",
      "awards": 2,
      "education": "Harvard University"
   },
   {
      "surname": "Sterling",
      "awards": 6,
      "education": "Polytechnic Institute of Brooklyn"
   },
   {
      "surname": "Stepanov",
      "awards": 0,
      "education": "Oxford University"
   },
   {
      "surname": "Stevens",
      "awards": 0,
      "education": "University of Michigan, University of Arizona"
   },
   {
      "surname": "Stockmeyer",
      "awards": 0,
      "education": "Oxford University"
   },
   {
      "surname": "Stolfo",
      "awards": 0,
      "education": "Brooklyn College"
   },
   {
      "surname": "Stonebraker",
      "awards": 2,
      "education": "Princeton University, University of Michigan"
   },
   {
      "surname": "Storaasli",
      "awards": 0,
      "education": "University of South Dakota"
   },
   {
      "surname": "Strachey",
      "awards": 0,
      "education": "King's College"
   },
   {
      "surname": "Strassen",
      "awards": 5,
      "education": "University of Göttingen"
   },
   {
      "surname": "Stroustrup",
      "awards": 6,
      "education": "Oxford University"
   },
   {
      "surname": "Sudan",
      "awards": 1,
      "education": "IIT Delhi, University of California"
   },
   {
      "surname": "Sussman",
      "awards": 2,
      "education": "Massachusetts Institute of Technology"
   },
   {
      "surname": "Sutherland",
      "awards": 1,
      "education": "Massachusetts Institute of Technology"
   },
   {
      "surname": "Sutherland",
      "awards": 12,
      "education": "Massachusetts Institute of Technology"
   },
   {
      "surname": "Sweeney",
      "awards": 0,
      "education": "Oxford University"
   },
   {
      "surname": "Szegedy",
      "awards": 1,
      "education": "University of Chicago"
   },
   {
      "surname": "Tabriz",
      "awards": 0,
      "education": "University of Illinois"
   },
   {
      "surname": "Tamassia",
      "awards": 4,
      "education": "University of Rome, University of Texas"
   },
   {
      "surname": "Tanenbaum",
      "awards": 22,
      "education": "Massachusetts Institute of Technology, University of California"
   },
   {
      "surname": "Tate",
      "awards": 1,
      "education": "Lancaster University"
   },
   {
      "surname": "Thalheim",
      "awards": 1,
      "education": "Dresden University of Technology, Lomonosov Moscow State University"
   },
   {
      "surname": "Tardos",
      "awards": 5,
      "education": "Eötvös University"
   },
   {
      "surname": "Tardos",
      "awards": 4,
      "education": "Eötvös University"
   },
   {
      "surname": "Tarjan",
      "awards": 8,
      "education": "Oxford University"
   },
   {
      "surname": "Taylor",
      "awards": 7,
      "education": "Purdue University"
   },
   {
      "surname": "Tchou",
      "awards": 0,
      "education": "Oxford University"
   },
   {
      "surname": "Teevan",
      "awards": 7,
      "education": "Yale University"
   },
   {
      "surname": "Teng",
      "awards": 1,
      "education": "Shanghai Jiao Tong University, University of Southern California"
   },
   {
      "surname": "Tesler",
      "awards": 0,
      "education": "Stanford University"
   },
   {
      "surname": "Avadis",
      "awards": 0,
      "education": "Carnegie Mellon University, University of Rochester"
   },
   {
      "surname": "Thacker",
      "awards": 3,
      "education": "University of California"
   },
   {
      "surname": "Thalmann",
      "awards": 4,
      "education": "University of Geneva"
   },
   {
      "surname": "Thompson",
      "awards": 9,
      "education": "Oxford University"
   },
   {
      "surname": "Thompson",
      "awards": 0,
      "education": "University of Oxford"
   },
   {
      "surname": "Thrun",
      "awards": 1,
      "education": "University of Hildesheim"
   },
   {
      "surname": "Tichy",
      "awards": 0,
      "education": "Technische Universität München, Carnegie Mellon University"
   },
   {
      "surname": "Toda",
      "awards": 0,
      "education": "Tokyo Institute of Technology"
   },
   {
      "surname": "Toh",
      "awards": 7,
      "education": "University of Cambridge, University of Manchester"
   },
   {
      "surname": "Torvalds",
      "awards": 13,
      "education": "University of Helsinki"
   },
   {
      "surname": "Quevedo",
      "awards": 1,
      "education": "Official School of the Road Engineers' Corps of Madrid"
   },
   {
      "surname": "Toussaint",
      "awards": 8,
      "education": "University of Tulsa, University of British Columbia"
   },
   {
      "surname": "Townsend",
      "awards": 1,
      "education": "Indiana University"
   },
   {
      "surname": "Tozer",
      "awards": 0,
      "education": "Oxford University"
   },
   {
      "surname": "Traub",
      "awards": 0,
      "education": "City College of New York, Columbia University"
   },
   {
      "surname": "Tucker",
      "awards": 0,
      "education": "University of Warwick"
   },
   {
      "surname": "Tukey",
      "awards": 6,
      "education": "Brown University, Princeton University"
   },
   {
      "surname": "Turing",
      "awards": 1,
      "education": "Oxford University"
   },
   {
      "surname": "Turner",
      "awards": 0,
      "education": "Oxford University"
   },
   {
      "surname": "Turoff",
      "awards": 1,
      "education": "University of California, Brandeis University"
   },
   {
      "surname": "Ullman",
      "awards": 4,
      "education": "Columbia University, Princeton University"
   },
   {
      "surname": "Valiant",
      "awards": 3,
      "education": "King's College"
   },
   {
      "surname": "Vapnik",
      "awards": 11,
      "education": "Uzbek State University"
   },
   {
      "surname": "Vardi",
      "awards": 3,
      "education": "Bar-Ilan University"
   },
   {
      "surname": "Vaughan",
      "awards": 7,
      "education": "Wilberforce University"
   },
   {
      "surname": "Vauquois",
      "awards": 0,
      "education": "Oxford University"
   },
   {
      "surname": "Vazirani",
      "awards": 1,
      "education": "Massachusetts Institute of Technology, University of California"
   },
   {
      "surname": "Veloso",
      "awards": 3,
      "education": "Lisbon's Instituto Superior Técnico"
   },
   {
      "surname": "Vernadat",
      "awards": 0,
      "education": "University of Clermont"
   },
   {
      "surname": "Veryard",
      "awards": 0,
      "education": "Merton College, Imperial College"
   },
   {
      "surname": "Vilkomir",
      "awards": 1,
      "education": "Kharkov State University, Kharkov Polytechnic Institute"
   },
   {
      "surname": "Vitányi",
      "awards": 8,
      "education": "Delft University of Technology, Free University of Amsterdam"
   },
   {
      "surname": "Viterbi",
      "awards": 8,
      "education": "Massachusetts Institute of Technology"
   },
   {
      "surname": "Vitter",
      "awards": 0,
      "education": "University of Notre Dame"
   },
   {
      "surname": "Vixie",
      "awards": 0,
      "education": "Keio University"
   },
   {
      "surname": "Wada",
      "awards": 0,
      "education": "University of Tokyo"
   },
   {
      "surname": "Wagner",
      "awards": 0,
      "education": "University of California"
   },
   {
      "surname": "Waltz",
      "awards": 2,
      "education": "Massachusetts Institute of Technology"
   },
   {
      "surname": "Wang",
      "awards": 2,
      "education": "University of Minnesota"
   },
   {
      "surname": "Ward",
      "awards": 0,
      "education": "Massachusetts Institute of Technology"
   },
   {
      "surname": "Warmuth",
      "awards": 1,
      "education": "University of Erlangen–Nuremberg, University of Colorado Boulder"
   },
   {
      "surname": "Warren",
      "awards": 0,
      "education": "University of Edinburgh"
   },
   {
      "surname": "Warwick",
      "awards": 4,
      "education": "Aston University, Imperial College London"
   },
   {
      "surname": "Węglarz",
      "awards": 0,
      "education": "Poznań University of Technology"
   },
   {
      "surname": "Wadler",
      "awards": 3,
      "education": "Stanford University, Carnegie Mellon University"
   },
   {
      "surname": "Wegner",
      "awards": 2,
      "education": "University of Cambridge"
   },
   {
      "surname": "Wegstein",
      "awards": 0,
      "education": "University of Illinois"
   },
   {
      "surname": "Weinberger",
      "awards": 0,
      "education": "University of California"
   },
   {
      "surname": "Weiser",
      "awards": 0,
      "education": "New College of Florida, University of Michigan"
   },
   {
      "surname": "Weizenbaum",
      "awards": 0,
      "education": "Wayne State University"
   },
   {
      "surname": "Wheeler",
      "awards": 3,
      "education": "Trinity College"
   },
   {
      "surname": "Westervelt",
      "awards": 0,
      "education": "University of California"
   },
   {
      "surname": "Whittaker",
      "awards": 5,
      "education": "University of Sheffield, University of California"
   },
   {
      "surname": "Widom",
      "awards": 6,
      "education": "Indiana University, Cornell University"
   },
   {
      "surname": "Wiederhold",
      "awards": 3,
      "education": "University of California"
   },
   {
      "surname": "Wiener",
      "awards": 9,
      "education": "Tufts College, Cornell University"
   },
   {
      "surname": "Adriaan",
      "awards": 4,
      "education": "Delft University of Technology"
   },
   {
      "surname": "Wilkes",
      "awards": 0,
      "education": "Wellesley College, Harvard University"
   },
   {
      "surname": "Wilkes",
      "awards": 5,
      "education": "University of California"
   },
   {
      "surname": "Wilks",
      "awards": 19,
      "education": "University of Cambridge"
   },
   {
      "surname": "Wilkinson",
      "awards": 3,
      "education": "Trinity College"
   },
   {
      "surname": "Wilson",
      "awards": 6,
      "education": "University of California"
   },
   {
      "surname": "Winograd",
      "awards": 0,
      "education": "New York University, Massachusetts Institute of Technology"
   },
   {
      "surname": "Winograd",
      "awards": 1,
      "education": "Massachusetts Institute of Technology"
   },
   {
      "surname": "Winston",
      "awards": 1,
      "education": "Massachusetts Institute of Technology"
   },
   {
      "surname": "Wirth",
      "awards": 5,
      "education": "University of California"
   },
   {
      "surname": "Wiseman",
      "awards": 0,
      "education": "Queen Mary College, University of London"
   },
   {
      "surname": "Wisnosky",
      "awards": 0,
      "education": "University of Pennsylvania"
   },
   {
      "surname": "Wolfram",
      "awards": 1,
      "education": "St. John's College, California Institute of Technology"
   },
   {
      "surname": "Woodger",
      "awards": 0,
      "education": "University College London"
   },
   {
      "surname": "Woodward",
      "awards": 3,
      "education": "Oxford University"
   },
   {
      "surname": "Worsley",
      "awards": 1,
      "education": "University of Toronto, Massachusetts Institute of Technology, University of Cambridge"
   },
   {
      "surname": "Wozniak",
      "awards": 0,
      "education": "University of Colorado Boulder, De Anza College, University of California"
   },
   {
      "surname": "Wu",
      "awards": 0,
      "education": "Temple University"
   },
   {
      "surname": "Wulf",
      "awards": 0,
      "education": "University of Illinois"
   },
   {
      "surname": "Yannakakis",
      "awards": 1,
      "education": "National Technical University of Athens, Princeton University"
   },
   {
      "surname": "Yao",
      "awards": 4,
      "education": "National Taiwan University, Harvard University"
   },
   {
      "surname": "Yen",
      "awards": 2,
      "education": "University of California, Santa Clara University, National Taiwan University"
   },
   {
      "surname": "Yoneda",
      "awards": 0,
      "education": "University of Tokyo"
   },
   {
      "surname": "Yourdon",
      "awards": 1,
      "education": "Massachusetts Institute of Technology"
   },
   {
      "surname": "Yung",
      "awards": 12,
      "education": "Columbia University"
   },
   {
      "surname": "Zadeh",
      "awards": 17,
      "education": "University of California"
   },
   {
      "surname": "Zantema",
      "awards": 0,
      "education": "University of Amsterdam"
   },
   {
      "surname": "Zaman",
      "awards": 0,
      "education": "Stanford University, Harvey Mudd College, Claremont Graduate University"
   },
   {
      "surname": "Zdonik",
      "awards": 0,
      "education": "Massachusetts Institute of Technology"
   },
   {
      "surname": "Zedan",
      "awards": 0,
      "education": "University of Bristol"
   },
   {
      "surname": "Zilberstein",
      "awards": 0,
      "education": "University of California, Israel Institute of Technology"
   },
   {
      "surname": "Zimmerman",
      "awards": 0,
      "education": "Massachusetts Institute of Technology"
   },
   {
      "surname": "Zuckerberg",
      "awards": 0,
      "education": "Harvard University"
   },
   {
      "surname": "Zuse",
      "awards": 5,
      "education": "Technische Universität Berlin"
   }
]